conformity/__init__.py
conformity/constants.py
conformity/error.py
conformity/py.typed
conformity/types.py
conformity/utils.py
conformity/validator.py
conformity/version.py
conformity/fields/__init__.py
conformity/fields/basic.py
conformity/fields/country.py
conformity/fields/currency.py
conformity/fields/email.py
conformity/fields/geo.py
conformity/fields/logging.py
conformity/fields/meta.py
conformity/fields/net.py
conformity/fields/structures.py
conformity/fields/temporal.py
conformity/fields/utils.py
conformity/settings/__init__.py
conformity/sphinx_ext/__init__.py
conformity/sphinx_ext/autodoc.py
conformity/sphinx_ext/linkcode.py
conformity/sphinx_ext/static/autodoc_auto_toc.js
conformity-1.28.2.dist-info/LICENSE
conformity-1.28.2.dist-info/METADATA
conformity-1.28.2.dist-info/WHEEL
conformity-1.28.2.dist-info/top_level.txt
conformity-1.28.2.dist-info/RECORD
