Metadata-Version: 2.1
Name: conformity
Version: 1.28.2
Summary: Cacheable schema description and validation
Home-page: http://github.com/eventbrite/conformity
Author: Eventbrite, Inc.
Author-email: opensource@eventbrite.com
License: Apache 2.0
Project-URL: Documentation, https://conformity.readthedocs.io
Project-URL: Issues, https://github.com/eventbrite/conformity/issues
Project-URL: CI, https://travis-ci.org/eventbrite/conformity/
Classifier: Development Status :: 5 - Production/Stable
Classifier: Intended Audience :: Developers
Classifier: License :: OSI Approved :: Apache Software License
Classifier: Operating System :: OS Independent
Classifier: Programming Language :: Python
Classifier: Programming Language :: Python :: 2
Classifier: Programming Language :: Python :: 2.7
Classifier: Programming Language :: Python :: 3
Classifier: Programming Language :: Python :: 3.5
Classifier: Programming Language :: Python :: 3.6
Classifier: Programming Language :: Python :: 3.7
Classifier: Programming Language :: Python :: 3.8
Classifier: Topic :: Software Development
Provides-Extra: currency
Provides-Extra: country
Provides-Extra: sphinx
Provides-Extra: docs
Provides-Extra: testing
Provides-Extra: mypy
License-File: LICENSE
